golf_federated/__init__.py
golf_federated/client/__init__.py
golf_federated/client/communication/__init__.py
golf_federated/client/communication/api/__init__.py
golf_federated/client/communication/api/download.py
golf_federated/client/communication/api/interact.py
golf_federated/client/communication/api/upload.py
golf_federated/client/communication/sse/__init__.py
golf_federated/client/communication/sse/monitor.py
golf_federated/client/process/__init__.py
golf_federated/client/process/config/__init__.py
golf_federated/client/process/config/device/__init__.py
golf_federated/client/process/config/device/base.py
golf_federated/client/process/config/device/multidevice.py
golf_federated/client/process/config/device/standalone.py
golf_federated/client/process/config/model/__init__.py
golf_federated/client/process/config/model/base.py
golf_federated/client/process/config/model/tfmodel.py
golf_federated/client/process/config/model/torchmodel.py
golf_federated/client/process/config/trainer/__init__.py
golf_federated/client/process/config/trainer/base.py
golf_federated/client/process/config/trainer/direct.py
golf_federated/client/process/config/trainer/docker.py
golf_federated/client/utils/__init__.py
golf_federated/server/__init__.py
golf_federated/server/communication/__init__.py
golf_federated/server/communication/api/__init__.py
golf_federated/server/communication/api/app.py
golf_federated/server/communication/api/download.py
golf_federated/server/communication/api/interact.py
golf_federated/server/communication/api/upload.py
golf_federated/server/communication/sse/__init__.py
golf_federated/server/communication/sse/schedule.py
golf_federated/server/process/__init__.py
golf_federated/server/process/config/__init__.py
golf_federated/server/process/config/device/__init__.py
golf_federated/server/process/config/device/base.py
golf_federated/server/process/config/device/multidevice.py
golf_federated/server/process/config/device/standalone.py
golf_federated-0.2.0.dist-info/AUTHORS.rst
golf_federated-0.2.0.dist-info/LICENSE
golf_federated-0.2.0.dist-info/METADATA
golf_federated-0.2.0.dist-info/WHEEL
golf_federated-0.2.0.dist-info/top_level.txt
golf_federated-0.2.0.dist-info/RECORD
