Metadata-Version: 2.1
Name: golf-federated
Version: 0.2.0
Summary: A scalable, portable, and lightweight Federated Learning framework.
Home-page: https://github.com/MatZaharia/generic_and_open_learning_federator
Author: MatZaharia
Author-email: guozh29@mail2.sysu.edu.cn
License: MIT license
Keywords: golf_federated
Platform: UNKNOWN
Classifier: Development Status :: 2 - Pre-Alpha
Classifier: Intended Audience :: Developers
Classifier: License :: OSI Approved :: MIT License
Classifier: Natural Language :: English
Classifier: Programming Language :: Python :: 3
Classifier: Programming Language :: Python :: 3.6
Classifier: Programming Language :: Python :: 3.7
Classifier: Programming Language :: Python :: 3.8
Requires-Python: >=3.6
